caf_verilog/__init__.py
caf_verilog/__version__.py
caf_verilog/arg_max.py
caf_verilog/caf.py
caf_verilog/caf_slice.py
caf_verilog/caf_verilog_base.py
caf_verilog/capture_buffer.py
caf_verilog/cpx_multiply.py
caf_verilog/dot_prod_pip.py
caf_verilog/dot_product.py
caf_verilog/freq_shift.py
caf_verilog/io_helper.py
caf_verilog/quantizer.py
caf_verilog/reference_buffer.py
caf_verilog/sig_gen.py
caf_verilog/sim_helper.py
caf_verilog/sqrt.py
caf_verilog/xcorr.py
src/arg_max.v
src/arg_max_inst.v
src/arg_max_tb.v
src/caf.v
src/caf_inst.v
src/caf_slice.v
src/caf_state_params.v
src/caf_tb.v
src/capture_buffer.v
src/capture_buffer_inst.v
src/capture_buffer_tb.v
src/cpx_multiply.v
src/cpx_multiply_inst.v
src/cpx_multiply_tb.v
src/dot_prod_inst.v
src/dot_prod_pip.v
src/dot_prod_pip_inst.v
src/dot_prod_pip_tb.v
src/dot_product.v
src/dot_product_tb.v
src/freq_shift.v
src/freq_shift_inst.v
src/freq_shift_tb.v
src/reference_buffer.v
src/reference_buffer_inst.v
src/reference_buffer_tb.v
src/sig_gen.v
src/sig_gen_inst.v
src/sig_gen_tb.v
src/x_corr.v
src/x_corr_inst.v
src/x_corr_tb.v
caf_verilog-0.13.0.dist-info/LICENSE
caf_verilog-0.13.0.dist-info/METADATA
caf_verilog-0.13.0.dist-info/WHEEL
caf_verilog-0.13.0.dist-info/top_level.txt
caf_verilog-0.13.0.dist-info/RECORD
