Metadata-Version: 2.1
Name: caf_verilog
Version: 0.13.0
Summary: CAF Verilog
Home-page: https://github.com/chiranthsiddappa/caf_verilog
Author: Chiranth Siddappa
Author-email: chiranthsiddappa@gmail.com
License: MIT
Requires-Python: >=3.4
License-File: LICENSE
Requires-Dist: scikit-dsp-comm ==2.0.1
Requires-Dist: numpy
Requires-Dist: Jinja2
Requires-Dist: inflection
